pagerduty/__init__.py
pagerduty/api_client.py
pagerduty/auth_method.py
pagerduty/cli.py
pagerduty/common.py
pagerduty/errors.py
pagerduty/events_api_v2_client.py
pagerduty/jira_cloud_integration_api_client.py
pagerduty/jira_server_integration_api_client.py
pagerduty/mcp_api_client.py
pagerduty/ms_teams_integration_api_client.py
pagerduty/oauth_token_client.py
pagerduty/py.typed
pagerduty/rest_api_v2_base_client.py
pagerduty/rest_api_v2_client.py
pagerduty/scim_api_client.py
pagerduty/slack_integration_api_client.py
pagerduty/slack_integration_connections_api_client.py
pagerduty/version.py
pagerduty-6.0.0.dist-info/licenses/LICENSE
pagerduty-6.0.0.dist-info/METADATA
pagerduty-6.0.0.dist-info/WHEEL
pagerduty-6.0.0.dist-info/entry_points.txt
pagerduty-6.0.0.dist-info/top_level.txt
pagerduty-6.0.0.dist-info/RECORD
